LICENSE.txt
README.md
setup.py
AlgosandDataStructure.egg-info/PKG-INFO
AlgosandDataStructure.egg-info/SOURCES.txt
AlgosandDataStructure.egg-info/dependency_links.txt
AlgosandDataStructure.egg-info/requires.txt
AlgosandDataStructure.egg-info/top_level.txt
AlgosandDataStructures/BinarySearch.py
AlgosandDataStructures/Dijkstra.py
AlgosandDataStructures/Fenwicktree.py
AlgosandDataStructures/Floydwarshall.py
AlgosandDataStructures/Lowerbound.py
AlgosandDataStructures/Stack.py
AlgosandDataStructures/Upperbound.py
AlgosandDataStructures/howtoGraph.py